{
  "sprintId": "sprint-004",
  "timestamp": "2025-12-29T14:30:00Z",
  "feature": {
    "number": 2,
    "name": "Audio Analyzer",
    "description": "Processes normalized audio data and extracts frequency spectrum and amplitude values in real-time using Web Audio API.",
    "dependencies": [1],
    "status": "in_progress"
  },
  "tests": [
    {
      "id": "2.1",
      "description": "Analyzer receives AudioBuffer from Audio Adapter",
      "status": "pending"
    },
    {
      "id": "2.2",
      "description": "Analyzer outputs frequency data as Float32Array (FFT)",
      "status": "pending"
    },
    {
      "id": "2.3",
      "description": "Analyzer outputs current amplitude as normalized 0-1 value",
      "status": "pending"
    },
    {
      "id": "2.4",
      "description": "Analyzer emits data at consistent frame rate (~60fps or requestAnimationFrame)",
      "status": "pending"
    },
    {
      "id": "2.5",
      "description": "Frequency data contains at least 64 bands",
      "status": "pending"
    },
    {
      "id": "2.6",
      "description": "Analyzer exposes configurable FFT size (256, 512, 1024, 2048)",
      "status": "pending"
    },
    {
      "id": "2.7",
      "description": "Analyzer continues outputting zero values when no audio is playing",
      "status": "pending"
    },
    {
      "id": "2.8",
      "description": "Analyzer can be paused and resumed",
      "status": "pending"
    },
    {
      "id": "2.9",
      "description": "Analyzer properly disconnects and cleans up on destroy()",
      "status": "pending"
    },
    {
      "id": "2.10",
      "description": "Amplitude smoothing is configurable (attack/release time)",
      "status": "pending"
    }
  ],
  "context": {
    "techStack": ["React", "TypeScript", "Web Audio API", "Canvas 2D"],
    "relevantFiles": [
      "src/core/AudioAdapter/AudioAdapter.ts",
      "src/types/audio.ts"
    ],
    "priorDecisions": [
      "Use Web Audio API AnalyserNode for FFT and amplitude",
      "Event emitter pattern for async callbacks",
      "AudioBufferReceiver interface for receiving buffers from AudioAdapter",
      "Lazy AudioContext initialization"
    ],
    "notes": "AudioAnalyzer should implement AudioBufferReceiver interface to integrate with AudioAdapter.connect()"
  },
  "status": "ready"
}
